Rhime/__init__.py
Rhime/ipa.py
Rhime/ipa_trie.py
Rhime/rhime.py
rhime-0.0.2.dist-info/licenses/LICENSE
rhime-0.0.2.dist-info/METADATA
rhime-0.0.2.dist-info/WHEEL
rhime-0.0.2.dist-info/top_level.txt
rhime-0.0.2.dist-info/RECORD
