Metadata-Version: 2.4
Name: Rhime
Version: 0.0.2
Summary: A python library to find rhymes of hindi words
Author-email: Anirudh Aswal <aswalanirudh@outlook.in>
License: GNU GENERAL PUBLIC LICENSE
Project-URL: Homepage, https://github.com/jupeeter8/Rhime
Project-URL: Issues, https://github.com/jupeeter8/Rhime/issues
Classifier: Programming Language :: Python :: 3
Classifier: Operating System :: OS Independent
Requires-Python: >=3.12
License-File: LICENSE
Requires-Dist: epitran
Dynamic: license-file
